zenfin/__init__.py
zenfin/stats.py
zenfin/utils.py
zenfin/version.py
zenfin-1.0.0.dist-info/METADATA
zenfin-1.0.0.dist-info/WHEEL
zenfin-1.0.0.dist-info/entry_points.txt
zenfin-1.0.0.dist-info/top_level.txt
zenfin-1.0.0.dist-info/RECORD
