Metadata-Version: 2.1
Name: zenfin
Version: 1.0.0
Summary: financial analysis toolbox
Home-page: https://github.com/zegoverno/zenfin
Author: José Governo
Author-email: zegoverno@hotmai.com
License: Apache Software License
Keywords: quant finance analysis portfolio
Platform: any
Classifier: Programming Language :: Python :: 3
Classifier: License :: OSI Approved :: Apache Software License
Classifier: Operating System :: OS Independent
Requires-Python: >=3.6
